lyle/__init__.py
lyle/math.py
tests/__init__.py
tests/test_math.py
lyle-0.9.2.dist-info/LICENSE
lyle-0.9.2.dist-info/LICENSE copy
lyle-0.9.2.dist-info/METADATA
lyle-0.9.2.dist-info/WHEEL
lyle-0.9.2.dist-info/top_level.txt
lyle-0.9.2.dist-info/RECORD
