Metadata-Version: 2.1
Name: lyle
Version: 0.9.2
Summary: Demo your first Test Pip package.
Home-page: https://github.com/lyleokoth/python-semantic-versioning
Author: Lyle Okoth
Author-email: lyleokoth@gmail.com
License: UNKNOWN
Project-URL: Homepage, https://github.com/lyleokoth/python-semantic-versioning
Keywords: pip-demo lyle
Platform: UNKNOWN
Classifier: Programming Language :: Python :: 3
Classifier: License :: OSI Approved :: MIT License
Classifier: Operating System :: OS Independent
Requires-Python: >=3.6
License-File: LICENSE
License-File: LICENSE copy
